README.rst
contextvars_executor.py
setup.cfg
setup.py
contextvars_executor.egg-info/PKG-INFO
contextvars_executor.egg-info/SOURCES.txt
contextvars_executor.egg-info/dependency_links.txt
contextvars_executor.egg-info/not-zip-safe
contextvars_executor.egg-info/top_level.txt