Metadata-Version: 1.2
Name: contextvars-executor
Version: 0.0.1
Summary: contextvars friendly ThreadPoolExecutor
Home-page: https://github.com/hellysmile/contextvars_executor
Author: Victor Kovtun
Author-email: hellysmile@gmail.com
License: UNKNOWN
Keywords: asyncio,contextvars
Platform: UNKNOWN
Classifier: Development Status :: 4 - Beta
Classifier: Intended Audience :: Developers
Classifier: License :: OSI Approved :: MIT License
Classifier: Programming Language :: Python
Classifier: Programming Language :: Python :: 3
Classifier: Programming Language :: Python :: 3.7
Requires-Python: >=3.7.0
